{
  "schema": 1,
  "packageId": "TorProject.TorBrowser",
  "status": "ExtractError",
  "hasIcon": false,
  "firstSeenUtc": "2026-04-20T18:03:01.6481268Z",
  "lastCheckedUtc": "2026-04-20T18:03:01.6481268Z",
  "lastUpdatedUtc": null,
  "wingetVersion": "v1.11.510",
  "packageVersion": null,
  "manifestSha": null,
  "installerType": null,
  "alreadyInstalled": false,
  "installedByThisRun": true,
  "installSeconds": 32,
  "extractSeconds": 0,
  "uninstallSeconds": 2,
  "durationSeconds": 36,
  "installExitCode": 0,
  "installTimedOut": false,
  "uninstallExitCode": -1978335212,
  "uninstallTimedOut": false,
  "iconCount": 0,
  "iconBytes": 0,
  "appIconFile": null,
  "canonicalIconSourceName": null,
  "canonicalIconBytes": null,
  "canonicalIconSha256": null,
  "extractError": "No ARP entries matched in scope 'Both' for 'TorProject.TorBrowser'. Is the package actually installed?",
  "installStdErr": null,
  "icons": null,
  "run": {
    "startedAtUtc": "2026-04-20T18:03:01.6481268Z",
    "runId": "24681908043",
    "runAttempt": "1",
    "repository": "awakecoding/winget-tools"
  }
}
