{
  "schema": 1,
  "packageId": "BinaryFortress.CloudShow",
  "resolvedPackageId": null,
  "status": "HasIcon",
  "hasIcon": true,
  "firstSeenUtc": "2026-04-25T18:11:05.6173682Z",
  "lastCheckedUtc": "2026-04-25T18:11:05.6173682Z",
  "lastUpdatedUtc": "2026-04-25T18:11:05.6173682Z",
  "wingetVersion": "v1.11.510",
  "packageVersion": null,
  "manifestSha": null,
  "installerType": null,
  "alreadyInstalled": false,
  "installedByThisRun": true,
  "installSeconds": 7,
  "extractSeconds": 0,
  "uninstallSeconds": 3,
  "durationSeconds": 11,
  "installExitCode": 0,
  "installTimedOut": false,
  "uninstallExitCode": 0,
  "uninstallTimedOut": false,
  "failureCategory": null,
  "installAttemptTag": "install-default",
  "extractAttemptCount": 1,
  "extractAttemptScopes": "Both",
  "extractFailureCategory": null,
  "iconCount": 1,
  "iconBytes": 144273.0,
  "appIconFile": "app-icon.ico",
  "canonicalIconSourceName": "CloudShow Launcher.7fb59370-6c93-47cd-91b7-c3eb75e76cd7_is1.ico",
  "canonicalIconBytes": 144273,
  "canonicalIconSha256": "40a684a7759ea08c13a13ab8666ec81dc06e5b149a39f5a6cfeef348b9a53001",
  "extractError": null,
  "installStdErr": null,
  "installAttempts": {
    "tag": "install-default",
    "exitCode": 0,
    "exitHex": "0x00000000",
    "timedOut": false,
    "errorName": null,
    "failureCategory": null
  },
  "icons": {
    "name": "CloudShow Launcher.7fb59370-6c93-47cd-91b7-c3eb75e76cd7_is1.ico",
    "bytes": 144273,
    "sha256": "40a684a7759ea08c13a13ab8666ec81dc06e5b149a39f5a6cfeef348b9a53001"
  },
  "run": {
    "startedAtUtc": "2026-04-25T18:11:05.6173682Z",
    "runId": "24919615418",
    "runAttempt": "1",
    "repository": "awakecoding/winget-tools"
  }
}
