{
  "schema": 1,
  "packageId": "BOMIST.BOMIST",
  "resolvedPackageId": null,
  "status": "HasIcon",
  "hasIcon": true,
  "firstSeenUtc": "2026-04-25T19:43:44.6228814Z",
  "lastCheckedUtc": "2026-04-25T19:43:44.6228814Z",
  "lastUpdatedUtc": "2026-04-25T19:43:44.6228814Z",
  "wingetVersion": "v1.11.510",
  "packageVersion": null,
  "manifestSha": null,
  "installerType": null,
  "alreadyInstalled": false,
  "installedByThisRun": true,
  "installSeconds": 42,
  "extractSeconds": 0,
  "uninstallSeconds": 4,
  "durationSeconds": 46,
  "installExitCode": 0,
  "installTimedOut": false,
  "uninstallExitCode": 0,
  "uninstallTimedOut": false,
  "failureCategory": null,
  "installAttemptTag": "install-default",
  "extractAttemptCount": 1,
  "extractAttemptScopes": "Both",
  "extractFailureCategory": null,
  "iconCount": 1,
  "iconBytes": 101777.0,
  "appIconFile": "app-icon.ico",
  "canonicalIconSourceName": "BOMIST 2.13.35.c5a7e6a8-fee1-5cad-8a77-23299446349e.ico",
  "canonicalIconBytes": 101777,
  "canonicalIconSha256": "a667073ebbf2620ebd89250dc6165d541b90765bbfec52b7261112ba359a5f40",
  "extractError": null,
  "installStdErr": null,
  "installAttempts": {
    "tag": "install-default",
    "exitCode": 0,
    "exitHex": "0x00000000",
    "timedOut": false,
    "errorName": null,
    "failureCategory": null
  },
  "icons": {
    "name": "BOMIST 2.13.35.c5a7e6a8-fee1-5cad-8a77-23299446349e.ico",
    "bytes": 101777,
    "sha256": "a667073ebbf2620ebd89250dc6165d541b90765bbfec52b7261112ba359a5f40"
  },
  "run": {
    "startedAtUtc": "2026-04-25T19:43:44.6228814Z",
    "runId": "24919615418",
    "runAttempt": "1",
    "repository": "awakecoding/winget-tools"
  }
}
