{
  "schema": 1,
  "packageId": "Baidu.SwanIDE",
  "resolvedPackageId": null,
  "status": "HasIcon",
  "hasIcon": true,
  "firstSeenUtc": "2026-04-25T06:38:48.4554377Z",
  "lastCheckedUtc": "2026-04-25T06:38:48.4554377Z",
  "lastUpdatedUtc": "2026-04-25T06:38:48.4554377Z",
  "wingetVersion": "v1.11.510",
  "packageVersion": null,
  "manifestSha": null,
  "installerType": null,
  "alreadyInstalled": false,
  "installedByThisRun": true,
  "installSeconds": 68,
  "extractSeconds": 0,
  "uninstallSeconds": 3,
  "durationSeconds": 72,
  "installExitCode": 0,
  "installTimedOut": false,
  "uninstallExitCode": 0,
  "uninstallTimedOut": false,
  "failureCategory": null,
  "installAttemptTag": "install-default",
  "extractAttemptCount": 1,
  "extractAttemptScopes": "Both",
  "extractFailureCategory": null,
  "iconCount": 1,
  "iconBytes": 31640.0,
  "appIconFile": "app-icon.ico",
  "canonicalIconSourceName": "百度开发者工具 4.36.1.47336783-caad-52d4-a900-9cc7c7c76434.ico",
  "canonicalIconBytes": 31640,
  "canonicalIconSha256": "99179e2cab560c9b64cc063acee4891b5bd3290644724de24cb9ef5e965a71c7",
  "extractError": null,
  "installStdErr": null,
  "installAttempts": {
    "tag": "install-default",
    "exitCode": 0,
    "exitHex": "0x00000000",
    "timedOut": false,
    "errorName": null,
    "failureCategory": null
  },
  "icons": {
    "name": "百度开发者工具 4.36.1.47336783-caad-52d4-a900-9cc7c7c76434.ico",
    "bytes": 31640,
    "sha256": "99179e2cab560c9b64cc063acee4891b5bd3290644724de24cb9ef5e965a71c7"
  },
  "run": {
    "startedAtUtc": "2026-04-25T06:38:48.4554377Z",
    "runId": "24908564742",
    "runAttempt": "1",
    "repository": "awakecoding/winget-tools"
  }
}
