{
  "schema": 1,
  "packageId": "RingCentral.RingCentralMeetingsRooms",
  "resolvedPackageId": null,
  "status": "HasIcon",
  "hasIcon": true,
  "firstSeenUtc": "2026-04-22T09:10:59.4718637Z",
  "lastCheckedUtc": "2026-04-22T09:10:59.4718637Z",
  "lastUpdatedUtc": "2026-04-22T09:10:59.4718637Z",
  "wingetVersion": "v1.11.510",
  "packageVersion": null,
  "manifestSha": null,
  "installerType": null,
  "alreadyInstalled": false,
  "installedByThisRun": true,
  "installSeconds": 37,
  "extractSeconds": 0,
  "uninstallSeconds": 10,
  "durationSeconds": 48,
  "installExitCode": 0,
  "installTimedOut": false,
  "uninstallExitCode": 0,
  "uninstallTimedOut": false,
  "failureCategory": null,
  "installAttemptTag": "install-default",
  "extractAttemptCount": 1,
  "extractAttemptScopes": "Both",
  "extractFailureCategory": null,
  "iconCount": 1,
  "iconBytes": 138849.0,
  "appIconFile": "app-icon.ico",
  "canonicalIconSourceName": "RingCentralRooms.RingCentralRooms.ico",
  "canonicalIconBytes": 138849,
  "canonicalIconSha256": "b73f31dc64d400117fda33501d65cca5812350497e8cef57aff1a068fd2d5da4",
  "extractError": null,
  "installStdErr": null,
  "installAttempts": {
    "tag": "install-default",
    "exitCode": 0,
    "exitHex": "0x00000000",
    "timedOut": false,
    "errorName": null,
    "failureCategory": null
  },
  "icons": {
    "name": "RingCentralRooms.RingCentralRooms.ico",
    "bytes": 138849,
    "sha256": "b73f31dc64d400117fda33501d65cca5812350497e8cef57aff1a068fd2d5da4"
  },
  "run": {
    "startedAtUtc": "2026-04-22T09:10:59.4718637Z",
    "runId": "24768741042",
    "runAttempt": "1",
    "repository": "awakecoding/winget-tools"
  }
}
